setup.py
firstHF.egg-info/PKG-INFO
firstHF.egg-info/SOURCES.txt
firstHF.egg-info/dependency_links.txt
firstHF.egg-info/top_level.txt
hf/__init__.py
hf/call_hf.py