Metadata-Version: 1.0
Name: firstHF
Version: 0.9.3
Summary: command line tool for auto tuner
Home-page: https://github.com/hf1154104163/hfRepository
Author: hanfei321
Author-email: 1154104163@qq.com
License: UNKNOWN
Platform: any
